mctthermalface/__init__.py
mctthermalface/mctthermalface.py
mctthermalface-0.2.2.dist-info/METADATA
mctthermalface-0.2.2.dist-info/WHEEL
mctthermalface-0.2.2.dist-info/top_level.txt
mctthermalface-0.2.2.dist-info/RECORD
